fabric_deployment_tool/__init__.py
fabric_deployment_tool/_fab_cli.py
fabric_deployment_tool/_fab_item_management.py
fabric_deployment_tool/_git.py
fabric_deployment_tool/_util.py
fabric_deployment_tool-0.1.2.dist-info/licenses/LICENSE
fabric_deployment_tool-0.1.2.dist-info/METADATA
fabric_deployment_tool-0.1.2.dist-info/WHEEL
fabric_deployment_tool-0.1.2.dist-info/entry_points.txt
fabric_deployment_tool-0.1.2.dist-info/top_level.txt
fabric_deployment_tool-0.1.2.dist-info/RECORD
