Metadata-Version: 2.4
Name: fabric-deployment-tool
Version: 0.1.2
Summary: Project for building distributable Fabric deployment tooling wheels.
Author-email: Edgar Cotte <e@e.com>
License: MIT License
Project-URL: Homepage, https://github.com/ecotte/fabric-deployment-tool
Project-URL: Issues, https://github.com/ecotte/fabric-deployment-tool/issues
Keywords: fabric,deployment,template,wheel
Classifier: Programming Language :: Python :: 3
Classifier: Programming Language :: Python :: 3 :: Only
Classifier: Programming Language :: Python :: 3.10
Classifier: License :: OSI Approved :: MIT License
Classifier: Operating System :: OS Independent
Requires-Python: >=3.10
License-File: LICENSE
Requires-Dist: typer>=0.12
Requires-Dist: rich>=13
Requires-Dist: ms-fabric-cli==1.2.0
Provides-Extra: dev
Requires-Dist: pytest>=8; extra == "dev"
Requires-Dist: pytest-cov>=5; extra == "dev"
Requires-Dist: ruff>=0.6; extra == "dev"
Requires-Dist: build>=1; extra == "dev"
Provides-Extra: cli
Requires-Dist: click>=8; extra == "cli"
Dynamic: license-file
